thumbnails/__init__.py
thumbnails/compat.py
thumbnails/conf.py
thumbnails/fields.py
thumbnails/files.py
thumbnails/images.py
thumbnails/metadata.py
thumbnails/models.py
thumbnails/post_processors.py
thumbnails/processors.py
thumbnails/utils.py
thumbnails/backends/__init__.py
thumbnails/backends/metadata.py
thumbnails/backends/storage.py
thumbnails/management/__init__.py
thumbnails/management/commands/__init__.py
thumbnails/management/commands/delete_thumbnails.py
thumbnails/migrations/0001_initial.py
thumbnails/migrations/__init__.py
thumbnails/south_migrations/0001_initial.py
thumbnails/south_migrations/__init__.py
thumbnails/tests/__init__.py
thumbnails/tests/metadata.py
thumbnails/tests/models.py
thumbnails/tests/settings.py
thumbnails/tests/storage.py
thumbnails/tests/test_commands.py
thumbnails/tests/test_fields.py
thumbnails/tests/test_files.py
thumbnails/tests/test_images.py
thumbnails/tests/test_metadata.py
thumbnails/tests/test_post_processors.py
thumbnails/tests/test_processors.py
thumbnails/tests/test_settings.py
django_thumbnails-0.8.0.dist-info/AUTHORS.txt
django_thumbnails-0.8.0.dist-info/LICENSE.txt
django_thumbnails-0.8.0.dist-info/METADATA
django_thumbnails-0.8.0.dist-info/WHEEL
django_thumbnails-0.8.0.dist-info/top_level.txt
django_thumbnails-0.8.0.dist-info/RECORD
