Metadata-Version: 2.1
Name: django-thumbnails
Version: 0.8.0
Summary: A simple Django app to manage image/photo thumbnails. Supports remote/cloud storage systems like Amazon S3.
Home-page: https://github.com/ui/django-thumbnails
Author: Selwin Ong
Author-email: selwin.ong@gmail.com
License: MIT
Classifier: Development Status :: 4 - Beta
Classifier: Environment :: Web Environment
Classifier: Framework :: Django
Classifier: Intended Audience :: Developers
Classifier: License :: OSI Approved :: MIT License
Classifier: Operating System :: OS Independent
Classifier: Programming Language :: Python
Classifier: Programming Language :: Python :: 3
Classifier: Programming Language :: Python :: 3.9
Classifier: Programming Language :: Python :: 3.10
Classifier: Programming Language :: Python :: 3.11
Classifier: Programming Language :: Python :: 3.12
Classifier: Topic :: Internet :: WWW/HTTP
Classifier: Topic :: Software Development :: Libraries :: Python Modules
Provides-Extra: redis
License-File: LICENSE.txt
License-File: AUTHORS.txt
